LocalAssistant/__init__.py
LocalAssistant/locas_config.json
LocalAssistant/main.py
LocalAssistant/parser.py
LocalAssistant/utils.py
LocalAssistant/model_processor/__init__.py
LocalAssistant/model_processor/chat.py
LocalAssistant/model_processor/docs.py
LocalAssistant/model_processor/download.py
LocalAssistant/model_processor/relation_extraction.py
LocalAssistant-1.1.2.dist-info/LICENSE
LocalAssistant-1.1.2.dist-info/METADATA
LocalAssistant-1.1.2.dist-info/WHEEL
LocalAssistant-1.1.2.dist-info/entry_points.txt
LocalAssistant-1.1.2.dist-info/top_level.txt
LocalAssistant-1.1.2.dist-info/RECORD
