Metadata-Version: 2.2
Name: LocalAssistant
Version: 1.1.2
Summary: LocalAssistant (locas) is an AI designed to be used in CLI. (Currently in development)
Author: Linos
Project-URL: Source, https://github.com/Linos1391/LocalAssistant
Classifier: Development Status :: 5 - Production/Stable
Classifier: Programming Language :: Python :: 3.10
Classifier: Programming Language :: Python :: 3.11
Classifier: Programming Language :: Python :: 3.12
Classifier: Natural Language :: English
Classifier: Intended Audience :: Developers
Classifier: License :: OSI Approved :: GNU General Public License v3 (GPLv3)
Classifier: Environment :: Console
Classifier: Environment :: GPU :: NVIDIA CUDA
Classifier: Operating System :: Microsoft :: Windows
Classifier: Operating System :: Unix
Requires-Python: >=3.10
License-File: LICENSE
Requires-Dist: transformers[torch]
Requires-Dist: bitsandbytes
Requires-Dist: sentence-transformers
Requires-Dist: PyMuPDF
Requires-Dist: sentencepiece
Requires-Dist: pyvis
Dynamic: author
Dynamic: classifier
Dynamic: description
Dynamic: description-content-type
Dynamic: project-url
Dynamic: requires-dist
Dynamic: requires-python
Dynamic: summary
